{
  "id": "大模型浪潮/第五章/1",
  "title": "第一节 手机：成为智能私人助理",
  "description": "智能手机的困境与大模型带来的新机遇",
  "source": "@site/terminology/大模型浪潮/第五章/第一节.md",
  "sourceDirName": "大模型浪潮/第五章",
  "slug": "/大模型浪潮/第五章/1",
  "permalink": "/terminology/大模型浪潮/第五章/1",
  "draft": false,
  "unlisted": false,
  "tags": [],
  "version": "current",
  "sidebarPosition": 1,
  "frontMatter": {
    "id": "1",
    "sidebar_position": 1,
    "title": "第一节 手机：成为智能私人助理",
    "hide_title": true
  },
  "sidebar": "termSidebar",
  "previous": {
    "title": "第四节 成熟应用一键集成",
    "permalink": "/terminology/大模型浪潮/第四章/4"
  },
  "next": {
    "title": "第二节 汽车：更智能、更舒适的“第三空间”",
    "permalink": "/terminology/大模型浪潮/第五章/2"
  }
}