{
  "id": "营销心理战/第三章/6",
  "title": "18 超限效应：不做营销界的“唐僧”",
  "description": "什么是“超限效应”：推多了反而让人逃跑",
  "source": "@site/docs/营销心理战/第三章/18 超限效应：不做营销界的“唐僧”.md",
  "sourceDirName": "营销心理战/第三章",
  "slug": "/营销心理战/第三章/6",
  "permalink": "/docs/营销心理战/第三章/6",
  "draft": false,
  "unlisted": false,
  "tags": [],
  "version": "current",
  "sidebarPosition": 6,
  "frontMatter": {
    "id": "6",
    "sidebar_position": 6,
    "title": "18 超限效应：不做营销界的“唐僧”",
    "hide_title": true
  },
  "sidebar": "bookSidebar",
  "previous": {
    "title": "17 场化效应：如此火爆的场面，怎么能不买",
    "permalink": "/docs/营销心理战/第三章/5"
  },
  "next": {
    "title": "19 从众效应：为什么群众的眼睛是雪亮的",
    "permalink": "/docs/营销心理战/第四章/1"
  }
}